django_plotly_dash/__init__.py
django_plotly_dash/_callback.py
django_plotly_dash/_patches.py
django_plotly_dash/access.py
django_plotly_dash/admin.py
django_plotly_dash/app_name.py
django_plotly_dash/apps.py
django_plotly_dash/consumers.py
django_plotly_dash/dash_wrapper.py
django_plotly_dash/finders.py
django_plotly_dash/middleware.py
django_plotly_dash/models.py
django_plotly_dash/routing.py
django_plotly_dash/tests.py
django_plotly_dash/tests_dash_contract.py
django_plotly_dash/urls.py
django_plotly_dash/util.py
django_plotly_dash/version.py
django_plotly_dash/views.py
django_plotly_dash/migrations/0001_initial.py
django_plotly_dash/migrations/0002_add_examples.py
django_plotly_dash/migrations/__init__.py
django_plotly_dash/templates/admin/django_plotly_dash/statelessapp/change_list.html
django_plotly_dash/templates/django_plotly_dash/plotly_app.html
django_plotly_dash/templates/django_plotly_dash/plotly_app_bootstrap.html
django_plotly_dash/templates/django_plotly_dash/plotly_direct.html
django_plotly_dash/templates/django_plotly_dash/plotly_messaging.html
django_plotly_dash/templatetags/__init__.py
django_plotly_dash/templatetags/plotly_dash.py
django_plotly_dash-2.4.7.dist-info/LICENSE
django_plotly_dash-2.4.7.dist-info/METADATA
django_plotly_dash-2.4.7.dist-info/WHEEL
django_plotly_dash-2.4.7.dist-info/top_level.txt
django_plotly_dash-2.4.7.dist-info/RECORD
