Metadata-Version: 2.1
Name: django-plotly-dash
Version: 2.4.7
Summary: Django use of plotly dash apps through template tags
Home-page: https://github.com/GibbsConsulting/django-plotly-dash
Author: Mark Gibbs
Author-email: django_plotly_dash@gibbsconsulting.ca
License: MIT
Project-URL: Source, https://github.com/GibbsConsulting/django-plotly-dash
Project-URL: Tracker, https://github.com/GibbsConsulting/django-plotly-dash/issues
Project-URL: Documentation, http://django-plotly-dash.readthedocs.io/
Keywords: django plotly plotly-dash dash dashboard
Classifier: Development Status :: 4 - Beta
Classifier: Intended Audience :: Developers
Classifier: License :: OSI Approved :: MIT License
Classifier: Programming Language :: Python :: 3
Classifier: Framework :: Dash
Requires-Python: >=3.8
License-File: LICENSE
Requires-Dist: plotly
Requires-Dist: dash<3.0,>=2.0
Requires-Dist: dpd-components
Requires-Dist: dash-bootstrap-components
Requires-Dist: channels>=4.0
Requires-Dist: Django>=4.0.0
Requires-Dist: Flask>=1.0.2
Requires-Dist: Werkzeug
